cepy_dict/__init__.py
cepy_dict/cc-cedict.txt
cepy_dict/cedict.py
cepy_dict-2025.2.20.dist-info/METADATA
cepy_dict-2025.2.20.dist-info/WHEEL
cepy_dict-2025.2.20.dist-info/licenses/COPYING
cepy_dict-2025.2.20.dist-info/RECORD
