Metadata-Version: 2.4
Name: cepy-dict
Version: 2025.2.20
Summary: A sleepy Chinese-english dictionary library
Author-email: Erik Swanson <theerikswanson@gmail.com>
License-Expression: GPL-3.0-or-later
License-File: COPYING
Requires-Python: >=3.8
